pwshc/__init__.py
pwshc/__main__.py
pwshc/_cmd.py
pwshc/_compile.py
pwshc/templates/out.cmd.jinja
pwshc-0.2.1.dist-info/entry_points.txt
pwshc-0.2.1.dist-info/METADATA
pwshc-0.2.1.dist-info/WHEEL
pwshc-0.2.1.dist-info/RECORD
